MaskAGref/MaskAGref.py
MaskAGref/__init__.py
getDsRNA/__init__.py
getDsRNA/step1_transcript_blat.py
getDsRNA/step2_transcript_dspair.py
getDsRNA/step3_bedtools_sorted_rmLC.py
getDsRNA/step4_combine_by_chr.py
getDsRNA/step5_merge_dsRNA.py
getDsRNA/step6_dsRNA.py
getRES/__init__.py
getRES/step1_SNVcalling.py
getRES/step2_annotation_based.py
getRES/step3_dsRNA_based.py
sprint2-0.1.dist-info/METADATA
sprint2-0.1.dist-info/WHEEL
sprint2-0.1.dist-info/entry_points.txt
sprint2-0.1.dist-info/top_level.txt
sprint2-0.1.dist-info/RECORD
